README.md
setup.cfg
setup.py
malfoy/__init__.py
malfoy.egg-info/PKG-INFO
malfoy.egg-info/SOURCES.txt
malfoy.egg-info/dependency_links.txt
malfoy.egg-info/top_level.txt