Metadata-Version: 1.0
Name: malfoy
Version: 0.0.1
Summary: Learning weights for Draco
Home-page: https://github.com/uwdata/draco-learn
Author: Dominik Moritz, Chenglong Wang
Author-email: domoritz@cs.washington.edu, clwang@cs.washington.edu
License: BSD-3
Platform: UNKNOWN
